AUTHORS.rst
CONTRIBUTING.rst
HISTORY.rst
LICENSE
MANIFEST.in
README.rst
setup.cfg
setup.py
docs/Makefile
docs/authors.rst
docs/conf.py
docs/contributing.rst
docs/history.rst
docs/index.rst
docs/installation.rst
docs/make.bat
docs/readme.rst
docs/usage.rst
kernelbridge/__init__.py
kernelbridge/basekernel.py
kernelbridge/cli.py
kernelbridge.egg-info/PKG-INFO
kernelbridge.egg-info/SOURCES.txt
kernelbridge.egg-info/dependency_links.txt
kernelbridge.egg-info/entry_points.txt
kernelbridge.egg-info/requires.txt
kernelbridge.egg-info/top_level.txt
kernelbridge.egg-info/zip-safe
tests/__init__.py
tests/test_kernelbridge.py