Metadata-Version: 1.2
Name: kernelbridge
Version: 0.1a1
Summary: Efficient, interoperable kernel creation and combination.
Home-page: https://github.com/drakejwong/kernelbridge
Author: Drake Wong
Author-email: drakejwong@gmail.com
License: BSD license
Keywords: kernelbridge
Platform: UNKNOWN
Classifier: Development Status :: 2 - Pre-Alpha
Classifier: Intended Audience :: Developers
Classifier: License :: OSI Approved :: BSD License
Classifier: Natural Language :: English
Classifier: Programming Language :: Python :: 3
Classifier: Programming Language :: Python :: 3.5
Classifier: Programming Language :: Python :: 3.6
Classifier: Programming Language :: Python :: 3.7
Classifier: Programming Language :: Python :: 3.8
Requires-Python: >=3.5
